yuuno/__init__.py
yuuno/autodiscover.py
yuuno/clip.py
yuuno/console_scripts.py
yuuno/standalone.py
yuuno/trait_types.py
yuuno/utils.py
yuuno/yuuno.py
yuuno/core/__init__.py
yuuno/core/environment.py
yuuno/core/extension.py
yuuno/core/namespace.py
yuuno/core/registry.py
yuuno/core/settings.py
yuuno/multi_scripts/__init__.py
yuuno/multi_scripts/environments.py
yuuno/multi_scripts/extension.py
yuuno/multi_scripts/script.py
yuuno/multi_scripts/utils.py
yuuno/multi_scripts/os/__init__.py
yuuno/multi_scripts/os/unix.py
yuuno/multi_scripts/os/win32.py
yuuno/multi_scripts/subprocess/__init__.py
yuuno/multi_scripts/subprocess/basic_commands.py
yuuno/multi_scripts/subprocess/clip.py
yuuno/multi_scripts/subprocess/manager.py
yuuno/multi_scripts/subprocess/process.py
yuuno/multi_scripts/subprocess/provider.py
yuuno/multi_scripts/subprocess/proxy.py
yuuno/output/__init__.py
yuuno/output/pil2png.py
yuuno/output/srgb_png.py
yuuno/vs/__init__.py
yuuno/vs/alpha.py
yuuno/vs/clip.py
yuuno/vs/extension.py
yuuno/vs/flags.py
yuuno/vs/provider.py
yuuno/vs/utils.py
yuuno/vs/vsscript/__init__.py
yuuno/vs/vsscript/capsules.py
yuuno/vs/vsscript/clip.py
yuuno/vs/vsscript/containermodule.py
yuuno/vs/vsscript/script.py
yuuno/vs/vsscript/vs_capi.py
yuuno_core-1.3.1.dist-info/AUTHORS.rst
yuuno_core-1.3.1.dist-info/COPYING
yuuno_core-1.3.1.dist-info/COPYING.LESSER
yuuno_core-1.3.1.dist-info/METADATA
yuuno_core-1.3.1.dist-info/WHEEL
yuuno_core-1.3.1.dist-info/entry_points.txt
yuuno_core-1.3.1.dist-info/top_level.txt
yuuno_core-1.3.1.dist-info/RECORD
