Metadata-Version: 2.1
Name: yuuno-core
Version: 1.3.1
Summary: Yuuno-Core - Extract frames from videos.
Home-page: https://github.com/stuxcrystal/yuuno-core
Author: stuxcrystal
Author-email: stuxcrystal@encode.moe
License: GNU Lesser General Public License v3 (LGPLv3)
Keywords: yuuno
Platform: UNKNOWN
Classifier: Natural Language :: English
Classifier: Development Status :: 5 - Production/Stable
Classifier: Intended Audience :: Developers
Classifier: Intended Audience :: Other Audience
Classifier: License :: OSI Approved :: GNU Lesser General Public License v3 (LGPLv3)
Classifier: Programming Language :: Python :: 3.6
Classifier: Topic :: Multimedia :: Video
Classifier: Topic :: Multimedia :: Video :: Display
Classifier: Topic :: Multimedia :: Video :: Non-Linear Editor
Requires-Dist: traitlets
Requires-Dist: pillow
Requires-Dist: psutil
Provides-Extra: vapoursynth
Requires-Dist: vapoursynth ; extra == 'vapoursynth'
